fact_explorer/app/frontend/static/404.html
fact_explorer/app/frontend/static/_next/static/chunks/29107295-a2d0c8e72019a3ed.js
fact_explorer/app/frontend/static/_next/static/chunks/429.243350cfd2557d21.js
fact_explorer/app/frontend/static/_next/static/chunks/502.d14b2e81e35c00e0.js
fact_explorer/app/frontend/static/_next/static/chunks/626-ca03c49cf2082b14.js
fact_explorer/app/frontend/static/_next/static/chunks/742-09836822a4157df7.js
fact_explorer/app/frontend/static/_next/static/chunks/framework-91d7f78b5b4003c8.js
fact_explorer/app/frontend/static/_next/static/chunks/main-7a03514cc6939943.js
fact_explorer/app/frontend/static/_next/static/chunks/pages/404-5d906dae850e37e0.js
fact_explorer/app/frontend/static/_next/static/chunks/pages/_app-38f15782a2008191.js
fact_explorer/app/frontend/static/_next/static/chunks/pages/_error-2280fa386d040b66.js
fact_explorer/app/frontend/static/_next/static/chunks/pages/index-40906e7533569cff.js
fact_explorer/app/frontend/static/_next/static/chunks/pages/search-c6ab8a97b02adfd4.js
fact_explorer/app/frontend/static/_next/static/chunks/polyfills-5cd94c89d3acac5f.js
fact_explorer/app/frontend/static/_next/static/chunks/webpack-5e73d14468dccc19.js
fact_explorer/app/frontend/static/_next/static/css/8dd5e3a6514bf33e.css
fact_explorer/app/frontend/static/_next/static/rHGH8HesiwAiqOXRL7ft6/_buildManifest.js
fact_explorer/app/frontend/static/_next/static/rHGH8HesiwAiqOXRL7ft6/_middlewareManifest.js
fact_explorer/app/frontend/static/_next/static/rHGH8HesiwAiqOXRL7ft6/_ssgManifest.js
fact_explorer/app/frontend/static/config.js
fact_explorer/app/frontend/static/favicon.png
fact_explorer/app/frontend/static/index.html
fact_explorer/app/frontend/static/search.html
fact_explorer/__init__.py
fact_explorer/app/__init__.py
fact_explorer/app/api/__init__.py
fact_explorer/app/api/constants.py
fact_explorer/app/api/registry.py
fact_explorer/app/api/router.py
fact_explorer/app/business/__init__.py
fact_explorer/app/business/crypto_helpers.py
fact_explorer-0.0.19.dist-info/entry_points.txt
fact_explorer-0.0.19.dist-info/LICENSE
fact_explorer-0.0.19.dist-info/WHEEL
fact_explorer-0.0.19.dist-info/METADATA
fact_explorer-0.0.19.dist-info/RECORD
